Metadata-Version: 2.1
Name: django-conversation
Version: 1.4.10
Summary: A reusable Django app that provides threaded conversations between users.
